constants.py
optiattack_client.py
example_app/__init__.py
example_app/example_app.py
optiattack_client-0.1.5.dist-info/METADATA
optiattack_client-0.1.5.dist-info/WHEEL
optiattack_client-0.1.5.dist-info/top_level.txt
optiattack_client-0.1.5.dist-info/RECORD
