Metadata-Version: 2.4
Name: optiattack_client
Version: 0.1.5
Summary: A FastAPI decorator to track method calls and manage state.
Home-page: https://github.com/OAResearch/optiattack
Author: Omur Sahin
Author-email: omur@erciyes.edu.tr
Classifier: Programming Language :: Python :: 3
Classifier: License :: OSI Approved :: GNU Lesser General Public License v3 (LGPLv3)
Classifier: Operating System :: OS Independent
Requires-Python: >=3.9
Requires-Dist: fastapi
Requires-Dist: uvicorn
Requires-Dist: python-multipart
Dynamic: author
Dynamic: author-email
Dynamic: classifier
Dynamic: description
Dynamic: description-content-type
Dynamic: home-page
Dynamic: requires-dist
Dynamic: requires-python
Dynamic: summary
